Metadata-Version: 2.4
Name: mseep-joern-mcp
Version: 0.1.4
Summary: A simple Joern MCP Server.
Author-email: mseep <support@skydeck.ai>
Requires-Python: >=3.10
License-File: LICENSE
Requires-Dist: python-dotenv>=1.0.1
Requires-Dist: fastmcp>=2.1.0
Requires-Dist: requests>=2.32.3
Dynamic: license-file
